{
    "Armes": [
        {
            "name": "TOURELLE 76/62 SUPER RAPIDE",
            "max_val": 281,
            "values": [
                227,
                262,
                248,
                248,
                249,
                229,
                239,
                249,
                227,
                230,
                232,
                251,
                234,
                246,
                231
            ]
        },
        {
            "name": "ARTILLERIE A COURTE PORTEE ET MUNITION",
            "max_val": 365,
            "values": [
                295,
                322,
                314,
                328,
                324,
                293,
                300,
                301,
                321,
                312,
                295,
                299,
                294,
                303,
                298
            ]
        },
        {
            "name": "CAISSON 20MM",
            "max_val": 946,
            "values": [
                766,
                779,
                839,
                835,
                775,
                811,
                819,
                840,
                797,
                777,
                759,
                843,
                796,
                802,
                785
            ]
        },
        {
            "name": "CONDUITE DE TIR",
            "max_val": 765,
            "values": [
                665,
                613,
                645,
                671,
                643,
                625,
                662,
                633,
                662,
                657,
                685,
                623,
                644,
                651,
                635
            ]
        },
        {
            "name": "GESTION DU SYSTEME DE LANCEMENT DES MISSILES ASTER",
            "max_val": 559,
            "values": [
                481,
                490,
                501,
                486,
                451,
                470,
                482,
                464,
                461,
                472,
                476,
                480,
                481,
                484,
                483
            ]
        },
        {
            "name": "GESTION DU SYSTEME DE LANCEMENT DES MISSILES SCALP",
            "max_val": 103,
            "values": [
                85,
                84,
                92,
                90,
                87,
                86,
                85,
                91,
                87,
                83,
                92,
                90,
                87,
                89,
                89
            ]
        },
        {
            "name": "SYSTEME LANCEMENT TORPILLE",
            "max_val": 802,
            "values": [
                693,
                675,
                698,
                673,
                691,
                671,
                694,
                710,
                672,
                647,
                677,
                682,
                674,
                658,
                685
            ]
        },
        {
            "name": "EWMLS",
            "max_val": 132,
            "values": [
                111,
                108,
                110,
                107,
                113,
                117,
                107,
                130,
                111,
                114,
                116,
                118,
                107,
                113,
                118
            ]
        },
        {
            "name": "SYSTEME LANCE-LEURRES ANTI SOUS-MARIN",
            "max_val": 184,
            "values": [
                156,
                153,
                151,
                148,
                159,
                147,
                164,
                150,
                158,
                153,
                163,
                152,
                159,
                150,
                158
            ]
        },
        {
            "name": "MANUTENTION DE L\'HELICO",
            "max_val": 92,
            "values": [
                74,
                75,
                81,
                74,
                76,
                78,
                82,
                81,
                99,
                80,
                80,
                74,
                79,
                81,
                78
            ]
        },
        {
            "name": "INSTALLATION MECANIQUE RELATIVE A L\'APPONTAGE DES HELICOPTERES",
            "max_val": 767,
            "values": [
                690,
                630,
                680,
                646,
                638,
                669,
                615,
                634,
                646,
                660,
                673,
                624,
                650,
                683,
                641
            ]
        }
    ],
    "Flotteur": [
        {
            "name": "REVETEMENTS DE PONT AUTRES QUE PEINTURE",
            "max_val": 732,
            "values": [
                597,
                656,
                604,
                610,
                622,
                644,
                607,
                597,
                655,
                599,
                618,
                621,
                627,
                654,
                607
            ]
        },
        {
            "name": "ELEMENTS D\'EMMENAGEMENT",
            "max_val": 380,
            "values": [
                312,
                337,
                329,
                304,
                335,
                340,
                338,
                317,
                327,
                313,
                340,
                332,
                311,
                311,
                337
            ]
        },
        {
            "name": "PROTECTION CATHODIQUE (PCCI)",
            "max_val": 164,
            "values": [
                136,
                135,
                138,
                133,
                131,
                146,
                132,
                140,
                138,
                140,
                145,
                141,
                147,
                134,
                135
            ]
        },
        {
            "name": "ELEMENTS DIVERS COQUE",
            "max_val": 290,
            "values": [
                244,
                288,
                249,
                242,
                247,
                254,
                253,
                253,
                234,
                249,
                245,
                241,
                259,
                244,
                258
            ]
        },
        {
            "name": "SUPERSTRUCTURES",
            "max_val": 451,
            "values": [
                379,
                368,
                380,
                392,
                387,
                368,
                368,
                374,
                396,
                390,
                400,
                390,
                365,
                361,
                405
            ]
        },
        {
            "name": "INSTALLATION IMMUNISATION",
            "max_val": 758,
            "values": [
                663,
                681,
                667,
                633,
                612,
                632,
                673,
                642,
                629,
                637,
                635,
                671,
                663,
                632,
                664
            ]
        },
        {
            "name": "STOCKAGE ET MAINTENANCE DE L\'HELICO",
            "max_val": 164,
            "values": [
                136,
                143,
                136,
                144,
                141,
                138,
                141,
                143,
                133,
                134,
                143,
                132,
                146,
                138,
                140
            ]
        },
        {
            "name": "INSTALLATION CARBUREACTEUR",
            "max_val": 552,
            "values": [
                467,
                465,
                461,
                457,
                493,
                493,
                478,
                485,
                474,
                464,
                485,
                602,
                494,
                457,
                451
            ]
        },
        {
            "name": "LOCAUX D\'EXPLOITATION AVIA",
            "max_val": 866,
            "values": [
                743,
                743,
                773,
                724,
                711,
                703,
                745,
                764,
                725,
                937,
                731,
                755,
                752,
                710,
                710
            ]
        },
        {
            "name": "INSTALLATION ENSEMBLE DES CADRES RABATTABLES",
            "max_val": 945,
            "values": [
                833,
                785,
                822,
                841,
                832,
                810,
                824,
                773,
                860,
                766,
                772,
                797,
                838,
                802,
                788
            ]
        },
        {
            "name": "IPMS ET OCMS",
            "max_val": 617,
            "values": [
                549,
                548,
                549,
                508,
                533,
                530,
                533,
                510,
                499,
                496,
                543,
                507,
                543,
                553,
                534
            ]
        },
        {
            "name": "APPAREIL A GOUVERNER - RUDDER ROLL",
            "max_val": 220,
            "values": [
                191,
                192,
                195,
                181,
                179,
                186,
                189,
                195,
                182,
                188,
                193,
                189,
                182,
                178,
                177
            ]
        },
        {
            "name": "CUISINE, BOULANGERIE, DEPENDANCES (COMMISSARY SPACES)",
            "max_val": 462,
            "values": [
                370,
                369,
                380,
                396,
                385,
                407,
                385,
                383,
                404,
                375,
                411,
                400,
                376,
                415,
                409
            ]
        },
        {
            "name": "INSTALLATIONS D\'AMARRAGE ET DE REMORQUAGE",
            "max_val": 794,
            "values": [
                672,
                635,
                641,
                636,
                680,
                642,
                655,
                713,
                688,
                815,
                683,
                695,
                654,
                683,
                638
            ]
        },
        {
            "name": "MISE EN RUVRE DES EMBARCATIONS LATERALES",
            "max_val": 622,
            "values": [
                540,
                502,
                550,
                539,
                514,
                504,
                541,
                513,
                522,
                506,
                529,
                498,
                516,
                550,
                535
            ]
        },
        {
            "name": "APPARAUX DE MANOEUVRE",
            "max_val": 308,
            "values": [
                266,
                252,
                251,
                273,
                255,
                276,
                275,
                251,
                267,
                274,
                251,
                246,
                271,
                263,
                261
            ]
        },
        {
            "name": "TRAITEMENT DU LINGE (LAUNDRY SPACES)",
            "max_val": 415,
            "values": [
                368,
                355,
                371,
                338,
                349,
                371,
                351,
                335,
                349,
                332,
                363,
                373,
                348,
                356,
                348
            ]
        },
        {
            "name": "TRAITEMENT EAUX HYDROCARBUREES",
            "max_val": 188,
            "values": [
                158,
                150,
                158,
                162,
                153,
                167,
                153,
                152,
                153,
                157,
                157,
                152,
                165,
                167,
                167
            ]
        },
        {
            "name": "INSTALLATIONS DE MOUILLAGE",
            "max_val": 666,
            "values": [
                591,
                551,
                565,
                550,
                583,
                569,
                550,
                546,
                548,
                591,
                592,
                580,
                576,
                542,
                533
            ]
        },
        {
            "name": "INSTALLATION DE R.A.M.",
            "max_val": 498,
            "values": [
                431,
                433,
                444,
                411,
                417,
                402,
                433,
                417,
                422,
                401,
                424,
                500,
                432,
                407,
                411
            ]
        },
        {
            "name": "STOCKAGE ET REFRIGERATION DES VIVRES",
            "max_val": 217,
            "values": [
                192,
                189,
                177,
                181,
                192,
                195,
                183,
                173,
                174,
                179,
                195,
                182,
                194,
                189,
                187
            ]
        },
        {
            "name": "AIR COMPRIME HP (MP ET BP), ACTIONNEURS PNEUMATIQUES",
            "max_val": 63,
            "values": [
                52,
                54,
                51,
                53,
                51,
                52,
                55,
                56,
                50,
                54,
                50,
                52,
                56,
                53,
                56
            ]
        },
        {
            "name": "EAU DOUCE CHAUDE ET FROIDE SERVICE GENERAL - EAU DEMINERALISEE",
            "max_val": 710,
            "values": [
                614,
                627,
                600,
                615,
                587,
                584,
                617,
                636,
                622,
                604,
                621,
                601,
                619,
                626,
                601
            ]
        },
        {
            "name": "GAZOLE",
            "max_val": 89,
            "values": [
                72,
                73,
                79,
                76,
                79,
                75,
                71,
                74,
                76,
                76,
                72,
                77,
                77,
                80,
                78
            ]
        },
        {
            "name": "EAU DOUCE REFRIGEREE A 6 DEGC",
            "max_val": 664,
            "values": [
                550,
                533,
                592,
                587,
                551,
                573,
                551,
                586,
                557,
                555,
                548,
                538,
                566,
                563,
                597
            ]
        },
        {
            "name": "ATELIERS (WORKSHOPS)",
            "max_val": 775,
            "values": [
                693,
                697,
                684,
                681,
                637,
                655,
                639,
                649,
                637,
                674,
                686,
                686,
                627,
                653,
                679
            ]
        }
    ],
    "Transmission": [
        {
            "name": "PROTECTION DES ACCES",
            "max_val": 91,
            "values": [
                78,
                74,
                75,
                78,
                75,
                80,
                80,
                81,
                74,
                73,
                76,
                72,
                79,
                79,
                75
            ]
        },
        {
            "name": "SOUS-SYSTEME TELESURVEILLANCE (CCTV)",
            "max_val": 45,
            "values": [
                39,
                38,
                38,
                38,
                40,
                36,
                36,
                39,
                36,
                37,
                40,
                37,
                40,
                37,
                38
            ]
        },
        {
            "name": "TELEPHONIE-VISIOCONFERENCE",
            "max_val": 215,
            "values": [
                193,
                189,
                176,
                188,
                176,
                179,
                181,
                174,
                182,
                174,
                180,
                189,
                183,
                177,
                178
            ]
        },
        {
            "name": "DISTRIBUTION-GESTION",
            "max_val": 785,
            "values": [
                692,
                648,
                696,
                657,
                633,
                646,
                664,
                692,
                644,
                635,
                672,
                684,
                662,
                673,
                688
            ]
        },
        {
            "name": "LIAISON DE DONNEES TACTIQUES",
            "max_val": 681,
            "values": [
                610,
                599,
                558,
                588,
                587,
                596,
                608,
                589,
                567,
                557,
                603,
                560,
                553,
                593,
                601
            ]
        },
        {
            "name": "SOUS-SYSTEME TELEPHONE AUTO GENERATEUR",
            "max_val": 748,
            "values": [
                611,
                622,
                716,
                600,
                656,
                635,
                603,
                673,
                671,
                666,
                620,
                631,
                608,
                664,
                651
            ]
        },
        {
            "name": "TERMINAL UTILISATEUR",
            "max_val": 874,
            "values": [
                783,
                708,
                714,
                778,
                756,
                701,
                786,
                702,
                701,
                766,
                710,
                771,
                750,
                747,
                752
            ]
        },
        {
            "name": "COMMUNICATIONS SATELLITES",
            "max_val": 840,
            "values": [
                694,
                688,
                674,
                690,
                756,
                750,
                681,
                679,
                740,
                703,
                728,
                677,
                738,
                725,
                676
            ]
        },
        {
            "name": "DIFFUSION ORDRES ALARMES",
            "max_val": 957,
            "values": [
                861,
                823,
                849,
                768,
                776,
                795,
                842,
                832,
                851,
                812,
                809,
                820,
                808,
                821,
                845
            ]
        },
        {
            "name": "HF",
            "max_val": 740,
            "values": [
                614,
                632,
                648,
                629,
                656,
                661,
                622,
                605,
                597,
                616,
                618,
                646,
                657,
                611,
                620
            ]
        },
        {
            "name": "SOUS-SYSTEME COMMUNICATIONS VOCALES MOBILES",
            "max_val": 730,
            "values": [
                649,
                588,
                593,
                621,
                589,
                652,
                642,
                657,
                623,
                633,
                636,
                622,
                614,
                627,
                645
            ]
        },
        {
            "name": "TELEBRIEFING",
            "max_val": 376,
            "values": [
                313,
                302,
                338,
                323,
                326,
                362,
                311,
                325,
                303,
                334,
                313,
                334,
                324,
                312,
                327
            ]
        },
        {
            "name": "DISTRACTION",
            "max_val": 608,
            "values": [
                506,
                533,
                533,
                512,
                546,
                539,
                507,
                544,
                539,
                512,
                526,
                537,
                487,
                502,
                523
            ]
        },
        {
            "name": "INSTALLATION TX",
            "max_val": 65,
            "values": [
                53,
                52,
                57,
                57,
                58,
                58,
                54,
                54,
                57,
                52,
                54,
                56,
                57,
                54,
                57
            ]
        },
        {
            "name": "EQUIPEMENTS DE MATURE",
            "max_val": 689,
            "values": [
                557,
                596,
                582,
                597,
                569,
                562,
                605,
                598,
                565,
                578,
                568,
                578,
                612,
                606,
                594
            ]
        },
        {
            "name": "INS NAVIRE",
            "max_val": 918,
            "values": [
                817,
                822,
                768,
                795,
                754,
                776,
                806,
                776,
                799,
                817,
                788,
                790,
                810,
                800,
                779
            ]
        }
    ],
    "Détection": [
        {
            "name": "RADAR MULTIFONCTIONS / IFF",
            "max_val": 907,
            "values": [
                730,
                784,
                773,
                779,
                801,
                795,
                810,
                776,
                741,
                795,
                788,
                739,
                743,
                782,
                768
            ]
        },
        {
            "name": "SYSTEME DE DETECTION ET DE PISTAGE INFRAROUGE FREMM",
            "max_val": 687,
            "values": [
                598,
                553,
                556,
                568,
                581,
                599,
                593,
                552,
                579,
                610,
                579,
                572,
                586,
                599,
                568
            ]
        },
        {
            "name": "RADAR CONTRE-MESURES (RECM)",
            "max_val": 434,
            "values": [
                361,
                358,
                389,
                373,
                377,
                371,
                388,
                353,
                354,
                382,
                390,
                385,
                372,
                378,
                358
            ]
        },
        {
            "name": "SYSTEME DE SURVEILLANCE RADIO-ELECTRIQUE RADAR (RESM) AVT",
            "max_val": 336,
            "values": [
                274,
                274,
                276,
                290,
                281,
                283,
                298,
                269,
                285,
                272,
                289,
                283,
                296,
                297,
                290
            ]
        },
        {
            "name": "SYSTEME LANCE LEURRES",
            "max_val": 859,
            "values": [
                768,
                690,
                726,
                721,
                689,
                703,
                702,
                740,
                697,
                757,
                704,
                708,
                749,
                748,
                771
            ]
        },
        {
            "name": "INTERCEPTION, ECOUTE, BROUILLAGE DES COMMUNICATIONS (CESM)",
            "max_val": 216,
            "values": [
                188,
                189,
                190,
                189,
                180,
                182,
                174,
                180,
                188,
                180,
                193,
                175,
                179,
                180,
                175
            ]
        },
        {
            "name": "INSTALLATION HR",
            "max_val": 651,
            "values": [
                566,
                521,
                562,
                529,
                553,
                530,
                580,
                561,
                548,
                528,
                577,
                557,
                535,
                560,
                564
            ]
        },
        {
            "name": "RADAR HELICOPTERE",
            "max_val": 391,
            "values": [
                313,
                349,
                313,
                333,
                332,
                318,
                340,
                332,
                343,
                343,
                314,
                333,
                347,
                322,
                345
            ]
        },
        {
            "name": "RADARS DE NAVIGATION",
            "max_val": 97,
            "values": [
                83,
                87,
                86,
                77,
                79,
                79,
                80,
                78,
                82,
                80,
                82,
                87,
                80,
                81,
                80
            ]
        },
        {
            "name": "SONAR D\'ETRAVE",
            "max_val": 773,
            "values": [
                618,
                667,
                662,
                688,
                690,
                664,
                632,
                692,
                664,
                619,
                628,
                675,
                632,
                653,
                666
            ]
        },
        {
            "name": "SONAR A IMMERSION VARIABLE",
            "max_val": 353,
            "values": [
                313,
                309,
                314,
                299,
                287,
                301,
                292,
                292,
                313,
                297,
                292,
                300,
                288,
                292,
                310
            ]
        },
        {
            "name": "TELEPHONE SOUS-MARIN",
            "max_val": 700,
            "values": [
                608,
                567,
                597,
                622,
                562,
                578,
                608,
                573,
                589,
                581,
                572,
                597,
                564,
                618,
                582
            ]
        },
        {
            "name": "MOBILIERS STANDARDS D\'AMENAGEMENT ET MOBILIER EN COURSIVE",
            "max_val": 256,
            "values": [
                221,
                225,
                216,
                224,
                223,
                225,
                208,
                223,
                218,
                209,
                214,
                205,
                215,
                223,
                221
            ]
        },
        {
            "name": "LOCAUX DIVERS",
            "max_val": 633,
            "values": [
                538,
                553,
                533,
                539,
                561,
                537,
                521,
                533,
                540,
                534,
                567,
                543,
                509,
                543,
                517
            ]
        },
        {
            "name": "CMD SUPPORT SYSTEM",
            "max_val": 280,
            "values": [
                233,
                231,
                224,
                247,
                235,
                229,
                249,
                244,
                243,
                235,
                232,
                240,
                232,
                233,
                240
            ]
        },
        {
            "name": "INSTALLATION CMS",
            "max_val": 501,
            "values": [
                424,
                401,
                417,
                421,
                430,
                405,
                407,
                413,
                433,
                442,
                446,
                402,
                439,
                402,
                450
            ]
        }
    ],
    "Énergie": [
        {
            "name": "RESEAU HAUTE TENSION 6,6 KV",
            "max_val": 565,
            "values": [
                549,
                476,
                483,
                473,
                491,
                504,
                498,
                454,
                479,
                452,
                468,
                492,
                502,
                458,
                488
            ]
        },
        {
            "name": "RESEAU DE SECOURS",
            "max_val": 114,
            "values": [
                93,
                91,
                91,
                92,
                93,
                102,
                101,
                99,
                96,
                102,
                97,
                99,
                99,
                92,
                93
            ]
        },
        {
            "name": "GROUPE DIESEL-ALTERNATEUR - ASPIRATIONS D\'AIR ET ECHAPPEMENTS HT",
            "max_val": 108,
            "values": [
                90,
                91,
                91,
                86,
                86,
                86,
                87,
                94,
                93,
                87,
                94,
                91,
                87,
                89,
                89
            ]
        },
        {
            "name": "ECLAIRAGE BORD - RESEAUX D\'ECLAIRAGE SPECIAUX",
            "max_val": 414,
            "values": [
                349,
                349,
                358,
                334,
                368,
                344,
                348,
                338,
                341,
                372,
                332,
                363,
                353,
                342,
                360
            ]
        },
        {
            "name": "RESEAU BT 60 HZ - DISTRIB. 440 ET 115 V.",
            "max_val": 760,
            "values": [
                682,
                622,
                659,
                647,
                664,
                609,
                620,
                626,
                666,
                628,
                616,
                626,
                666,
                674,
                657
            ]
        },
        {
            "name": "RESEAU ELECTRO-DOMESTIQUE 220 V - 60 HZ",
            "max_val": 495,
            "values": [
                419,
                425,
                403,
                430,
                411,
                414,
                421,
                430,
                440,
                420,
                429,
                425,
                431,
                419,
                431
            ]
        },
        {
            "name": "INSTALLATIONS ELECTRIQUES RELATIVES A L\'APPONTAGE DES HELICOPTERES",
            "max_val": 69,
            "values": [
                60,
                56,
                55,
                60,
                62,
                55,
                59,
                59,
                57,
                58,
                62,
                59,
                58,
                60,
                56
            ]
        }
    ],
    "Navigation": [
        {
            "name": "FEUX NAVIGATION",
            "max_val": 117,
            "values": [
                102,
                99,
                105,
                93,
                97,
                100,
                102,
                95,
                98,
                102,
                103,
                97,
                98,
                99,
                97
            ]
        },
        {
            "name": "SYSTEME DE NAVIGATION BASIQUE",
            "max_val": 475,
            "values": [
                402,
                410,
                427,
                392,
                389,
                398,
                423,
                421,
                390,
                419,
                422,
                410,
                398,
                420,
                427
            ]
        },
        {
            "name": "SYSTEME DE DONNEES NAVIGATION",
            "max_val": 780,
            "values": [
                632,
                667,
                694,
                692,
                649,
                652,
                661,
                628,
                642,
                687,
                675,
                641,
                688,
                637,
                681
            ]
        },
        {
            "name": "SYSTEME DE RADIONAVIGATION",
            "max_val": 59,
            "values": [
                51,
                49,
                48,
                47,
                48,
                48,
                50,
                48,
                47,
                47,
                47,
                47,
                53,
                53,
                49
            ]
        },
        {
            "name": "SYSTEME DE VISUALISATION DONNEES DE NAV",
            "max_val": 296,
            "values": [
                266,
                254,
                244,
                241,
                240,
                257,
                263,
                244,
                239,
                248,
                252,
                263,
                262,
                245,
                253
            ]
        },
        {
            "name": "SYSTEME ENVIRONNEMENT AIR ET EAU",
            "max_val": 678,
            "values": [
                568,
                548,
                595,
                586,
                594,
                574,
                549,
                593,
                560,
                587,
                572,
                609,
                542,
                565,
                563
            ]
        },
        {
            "name": "CONDUITE NAUTIQUE IBS",
            "max_val": 764,
            "values": [
                686,
                678,
                648,
                611,
                619,
                667,
                658,
                631,
                647,
                666,
                647,
                671,
                679,
                621,
                660
            ]
        }
    ],
    "Propulsion": [
        {
            "name": "LIGNES D\'ARBRES / HELICES",
            "max_val": 785,
            "values": [
                692,
                694,
                688,
                693,
                639,
                671,
                658,
                671,
                655,
                687,
                693,
                836,
                634,
                662,
                680
            ]
        },
        {
            "name": "EQUIPEMENTS ELECTRIQUES DE PROPULSION",
            "max_val": 390,
            "values": [
                328,
                328,
                348,
                339,
                342,
                312,
                327,
                338,
                397,
                334,
                318,
                315,
                315,
                339,
                348
            ]
        },
        {
            "name": "PROPULSION AUXILIAIRE",
            "max_val": 740,
            "values": [
                618,
                666,
                617,
                663,
                627,
                622,
                664,
                661,
                637,
                614,
                663,
                621,
                593,
                629,
                627
            ]
        },
        {
            "name": "SYSTEME DE CONDUITE DE LA PROPULSION PRINCIPALE",
            "max_val": 413,
            "values": [
                334,
                358,
                344,
                352,
                370,
                361,
                369,
                338,
                352,
                339,
                362,
                350,
                360,
                335,
                336
            ]
        },
        {
            "name": "REDUCTEUR",
            "max_val": 291,
            "values": [
                233,
                239,
                241,
                246,
                250,
                235,
                234,
                256,
                255,
                261,
                258,
                247,
                255,
                236,
                258
            ]
        },
        {
            "name": "TURBINE A GAZ",
            "max_val": 649,
            "values": [
                535,
                544,
                557,
                530,
                540,
                564,
                537,
                532,
                564,
                520,
                568,
                570,
                550,
                571,
                522
            ]
        },
        {
            "name": "LUBRIFIANTS",
            "max_val": 972,
            "values": [
                817,
                837,
                827,
                854,
                869,
                849,
                840,
                847,
                792,
                862,
                801,
                780,
                839,
                873,
                786
            ]
        }
    ],
    "Sécurité": [
        {
            "name": "LOCAUX HYGIENE (SANITARY SPACES)",
            "max_val": 838,
            "values": [
                729,
                727,
                705,
                693,
                779,
                743,
                672,
                741,
                688,
                748,
                679,
                718,
                734,
                685,
                685
            ]
        },
        {
            "name": "EAUX NOIRES ET EAUX GRISES",
            "max_val": 839,
            "values": [
                686,
                734,
                745,
                754,
                696,
                681,
                745,
                673,
                751,
                697,
                717,
                737,
                750,
                731,
                705
            ]
        },
        {
            "name": "AUTRES APPAREILS DE LEVAGE ET DE MANUTENTION",
            "max_val": 42,
            "values": [
                35,
                35,
                36,
                34,
                37,
                35,
                35,
                35,
                34,
                35,
                35,
                36,
                36,
                35,
                36
            ]
        },
        {
            "name": "VCCA, DESHUMIDIFICATION",
            "max_val": 507,
            "values": [
                446,
                407,
                441,
                438,
                439,
                464,
                409,
                451,
                432,
                417,
                439,
                439,
                432,
                418,
                415
            ]
        },
        {
            "name": "PROTECTION CONTRE LES VOIES D\'EAU",
            "max_val": 706,
            "values": [
                596,
                574,
                566,
                635,
                618,
                620,
                611,
                620,
                571,
                625,
                611,
                628,
                631,
                575,
                585
            ]
        },
        {
            "name": "PROTECTION CONTRE L\'INCENDIE",
            "max_val": 547,
            "values": [
                452,
                463,
                474,
                459,
                469,
                471,
                466,
                475,
                451,
                453,
                441,
                492,
                471,
                468,
                462
            ]
        },
        {
            "name": "EAU DE MER : INCENDIE, LAVAGE, REFRIGERATION AUXILIAIRES",
            "max_val": 558,
            "values": [
                451,
                493,
                479,
                493,
                458,
                472,
                498,
                466,
                480,
                478,
                460,
                499,
                463,
                468,
                494
            ]
        },
        {
            "name": "PROTECTION CONTRE AGRESSIFS NBC",
            "max_val": 79,
            "values": [
                70,
                65,
                70,
                66,
                65,
                68,
                70,
                65,
                63,
                69,
                67,
                63,
                67,
                71,
                66
            ]
        },
        {
            "name": "REDRESSEMENT",
            "max_val": 678,
            "values": [
                548,
                602,
                545,
                577,
                609,
                586,
                558,
                609,
                573,
                609,
                554,
                566,
                601,
                598,
                593
            ]
        },
        {
            "name": "FERMETURES DIVERSES",
            "max_val": 338,
            "values": [
                303,
                288,
                295,
                284,
                291,
                284,
                301,
                284,
                284,
                283,
                275,
                292,
                291,
                303,
                274
            ]
        },
        {
            "name": "INFIRMERIE ET CIRCUITS OXYGENOTHERAPIE",
            "max_val": 169,
            "values": [
                152,
                135,
                137,
                143,
                141,
                141,
                148,
                146,
                145,
                139,
                144,
                147,
                141,
                139,
                150
            ]
        },
        {
            "name": "LOCAUX VIE",
            "max_val": 103,
            "values": [
                82,
                82,
                91,
                88,
                92,
                83,
                87,
                92,
                89,
                83,
                91,
                83,
                92,
                85,
                87
            ]
        },
        {
            "name": "ZONE RESTAURATION",
            "max_val": 948,
            "values": [
                852,
                825,
                818,
                760,
                812,
                822,
                829,
                835,
                763,
                813,
                811,
                767,
                842,
                765,
                806
            ]
        }
    ]
}